fatima_utils/__init__.py
fatima_utils/calculator.py
fatima_utils/formatter.py
fatimaismail_utils-1.0.1.dist-info/licenses/LICENSE
fatimaismail_utils-1.0.1.dist-info/METADATA
fatimaismail_utils-1.0.1.dist-info/WHEEL
fatimaismail_utils-1.0.1.dist-info/top_level.txt
fatimaismail_utils-1.0.1.dist-info/RECORD
